julie/main.py
julie-0.1.0.dist-info/LICENSE
julie-0.1.0.dist-info/METADATA
julie-0.1.0.dist-info/WHEEL
julie-0.1.0.dist-info/entry_points.txt
julie-0.1.0.dist-info/RECORD
